MonkeyScope.cpython-311-darwin.so
MonkeyScope-1.6.0.dist-info/LICENSE
MonkeyScope-1.6.0.dist-info/METADATA
MonkeyScope-1.6.0.dist-info/WHEEL
MonkeyScope-1.6.0.dist-info/top_level.txt
MonkeyScope-1.6.0.dist-info/RECORD
