Metadata-Version: 2.1
Name: MonkeyScope
Version: 1.6.0
Summary: Distributions & Timer for Non-deterministic Value Generators
Home-page: https://github.com/BrokenShell/MonkeyScope
Author: Robert Sharp
Author-email: webmaster@sharpdesigndigital.com
License: Free for non-commercial use
Keywords: MonkeyScope,distribution tests,function timer,performance testing,statistical analysis
Platform: Darwin
Platform: Linux
Classifier: Development Status :: 5 - Production/Stable
Classifier: Programming Language :: Python :: 3.7
Classifier: Programming Language :: Cython
Classifier: Operating System :: MacOS :: MacOS X
Classifier: Operating System :: POSIX :: Linux
Classifier: Topic :: Software Development :: Libraries :: Python Modules
Requires-Python: >=3.7
License-File: LICENSE
